[{"hno":26210,"hnm":"연지자이2차","typeNm":"아파트","callPrice":1500.42,"realPrice":1345.36,"kbPrice":1389.05,"call_KB":108.01,"real_KB":96.85,"callCount":97,"realCount":27},{"hno":5224,"hnm":"연지로얄","typeNm":"아파트","callPrice":1480.41,"realPrice":1229.83,"kbPrice":1461.81,"call_KB":101.27,"real_KB":84.13,"callCount":13,"realCount":1},{"hno":23739,"hnm":"연지자이1차","typeNm":"아파트","callPrice":1375.12,"realPrice":1223.94,"kbPrice":1266.23,"call_KB":108.59,"real_KB":96.66,"callCount":41,"realCount":12},{"hno":124845,"hnm":"연지보해이브더파크(주상복합)","typeNm":"아파트","callPrice":1320.29,"realPrice":null,"kbPrice":1124.95,"call_KB":117.36,"real_KB":null,"callCount":13,"realCount":0},{"hno":111473,"hnm":"연지삼정그린코아(주상복합)","typeNm":"아파트","callPrice":1173.33,"realPrice":1083.79,"kbPrice":1139.5,"call_KB":102.96,"real_KB":95.11,"callCount":3,"realCount":4},{"hno":5245,"hnm":"일동대영","typeNm":"재건축","callPrice":1097.53,"realPrice":978.9,"kbPrice":1015.18,"call_KB":108.11,"real_KB":96.42,"callCount":11,"realCount":1},{"hno":5238,"hnm":"삼익","typeNm":"아파트","callPrice":1042.52,"realPrice":860.34,"kbPrice":1028.46,"call_KB":101.36,"real_KB":83.65,"callCount":11,"realCount":2},{"hno":13961,"hnm":"유림노르웨이숲","typeNm":"아파트","callPrice":1039.25,"realPrice":980.43,"kbPrice":993.81,"call_KB":104.57,"real_KB":98.65,"callCount":12,"realCount":4},{"hno":23110,"hnm":"금오파크뷰(주상복합)","typeNm":"아파트","callPrice":947.31,"realPrice":null,"kbPrice":814.83,"call_KB":116.25,"real_KB":null,"callCount":4,"realCount":0},{"hno":5244,"hnm":"화인","typeNm":"아파트","callPrice":914.34,"realPrice":838.88,"kbPrice":879.74,"call_KB":103.93,"real_KB":95.35,"callCount":27,"realCount":16},{"hno":5246,"hnm":"연지청구1차","typeNm":"아파트","callPrice":891.91,"realPrice":833.56,"kbPrice":869.41,"call_KB":102.58,"real_KB":95.87,"callCount":35,"realCount":7},{"hno":5243,"hnm":"세동한신","typeNm":"아파트","callPrice":852.78,"realPrice":783.23,"kbPrice":812.5,"call_KB":104.95,"real_KB":96.39,"callCount":42,"realCount":10},{"hno":25446,"hnm":"연지경동(메르빌)","typeNm":"아파트","callPrice":788.13,"realPrice":700.78,"kbPrice":835.05,"call_KB":94.38,"real_KB":83.92,"callCount":29,"realCount":2},{"hno":5247,"hnm":"연지한신타워","typeNm":"아파트","callPrice":780.58,"realPrice":730.52,"kbPrice":742.47,"call_KB":105.13,"real_KB":98.39,"callCount":28,"realCount":6},{"hno":9028,"hnm":"연지청구2차","typeNm":"아파트","callPrice":764.34,"realPrice":673.43,"kbPrice":737.74,"call_KB":103.6,"real_KB":91.28,"callCount":32,"realCount":10}]