[{"hno":109738,"hnm":"무전희가로","typeNm":"아파트","callPrice":897.02,"realPrice":870.45,"kbPrice":891.07,"call_KB":100.66,"real_KB":97.68,"callCount":4,"realCount":0},{"hno":17461,"hnm":"한진로즈힐비치1차","typeNm":"아파트","callPrice":854.13,"realPrice":824.16,"kbPrice":832.48,"call_KB":102.59,"real_KB":99,"callCount":21,"realCount":9},{"hno":101112,"hnm":"한진로즈힐비치2차","typeNm":"아파트","callPrice":814.01,"realPrice":833.99,"kbPrice":857.05,"call_KB":94.97,"real_KB":97.3,"callCount":27,"realCount":8},{"hno":101117,"hnm":"주영에이스빌4차","typeNm":"아파트","callPrice":775.97,"realPrice":null,"kbPrice":740.7,"call_KB":104.76,"real_KB":null,"callCount":1,"realCount":0},{"hno":101114,"hnm":"주영에이스빌2차(주상복합)","typeNm":"아파트","callPrice":763.86,"realPrice":null,"kbPrice":763.86,"call_KB":100,"real_KB":null,"callCount":1,"realCount":0},{"hno":101118,"hnm":"주영에이스빌5차","typeNm":"아파트","callPrice":752.17,"realPrice":null,"kbPrice":662.79,"call_KB":113.48,"real_KB":null,"callCount":5,"realCount":0},{"hno":101123,"hnm":"일성르네상스","typeNm":"아파트","callPrice":719.45,"realPrice":720.88,"kbPrice":714.45,"call_KB":100.7,"real_KB":100.9,"callCount":13,"realCount":1},{"hno":107850,"hnm":"수아지오","typeNm":"아파트","callPrice":710.58,"realPrice":614.84,"kbPrice":719.53,"call_KB":98.75,"real_KB":85.45,"callCount":3,"realCount":1},{"hno":100931,"hnm":"일성한샘빌라2차","typeNm":"아파트","callPrice":708.42,"realPrice":null,"kbPrice":636.55,"call_KB":111.29,"real_KB":null,"callCount":2,"realCount":0},{"hno":101116,"hnm":"주영에이스빌1차(주상복합)","typeNm":"아파트","callPrice":692.4,"realPrice":705.66,"kbPrice":700.07,"call_KB":98.9,"real_KB":100.79,"callCount":1,"realCount":2},{"hno":101121,"hnm":"동성테크빌","typeNm":"아파트","callPrice":688.29,"realPrice":null,"kbPrice":657,"call_KB":104.76,"real_KB":null,"callCount":1,"realCount":0},{"hno":16879,"hnm":"진우하이빌1차(주상복합)","typeNm":"아파트","callPrice":639.31,"realPrice":null,"kbPrice":613.73,"call_KB":104.16,"real_KB":null,"callCount":2,"realCount":0},{"hno":101115,"hnm":"주영에이스빌3차(주상복합)","typeNm":"아파트","callPrice":633.57,"realPrice":717.34,"kbPrice":617.9,"call_KB":102.53,"real_KB":116.09,"callCount":2,"realCount":1},{"hno":16874,"hnm":"일성한샘1차","typeNm":"아파트","callPrice":632.46,"realPrice":623.24,"kbPrice":618.17,"call_KB":102.31,"real_KB":100.81,"callCount":3,"realCount":1},{"hno":101120,"hnm":"진우하이빌3차","typeNm":"아파트","callPrice":632.33,"realPrice":655.03,"kbPrice":632.33,"call_KB":100,"real_KB":103.58,"callCount":1,"realCount":1},{"hno":122211,"hnm":"더뷰(주상복합)","typeNm":"아파트","callPrice":624.49,"realPrice":535.38,"kbPrice":616.72,"call_KB":101.26,"real_KB":86.81,"callCount":5,"realCount":1},{"hno":101119,"hnm":"진우하이빌2차(주상복합)","typeNm":"아파트","callPrice":572.29,"realPrice":560.85,"kbPrice":587.64,"call_KB":97.38,"real_KB":95.44,"callCount":1,"realCount":2},{"hno":16877,"hnm":"주영한사랑","typeNm":"아파트","callPrice":560.05,"realPrice":null,"kbPrice":449.33,"call_KB":124.64,"real_KB":null,"callCount":8,"realCount":0},{"hno":107224,"hnm":"휴엔하임(주상복합)","typeNm":"아파트","callPrice":null,"realPrice":711.57,"kbPrice":711.57,"call_KB":null,"real_KB":100,"callCount":null,"realCount":1},{"hno":16876,"hnm":"일성한솔타운(주상복합)","typeNm":"아파트","callPrice":null,"realPrice":442.02,"kbPrice":472.66,"call_KB":null,"real_KB":93.51,"callCount":null,"realCount":1}]