[{"hno":2982,"hnm":"강변래미안","typeNm":"아파트","callPrice":3925.54,"realPrice":3689.34,"kbPrice":3530.33,"call_KB":111.19,"real_KB":104.5,"callCount":51,"realCount":3},{"hno":676,"hnm":"래미안당산1차","typeNm":"아파트","callPrice":3684.14,"realPrice":3981.15,"kbPrice":3326.23,"call_KB":110.76,"real_KB":119.68,"callCount":8,"realCount":1},{"hno":11208,"hnm":"드림리버빌","typeNm":"아파트","callPrice":3128.85,"realPrice":2882.3,"kbPrice":2751.84,"call_KB":113.7,"real_KB":104.74,"callCount":8,"realCount":2},{"hno":23259,"hnm":"드림시드(주상복합)","typeNm":"아파트","callPrice":2422.82,"realPrice":1973.33,"kbPrice":2220,"call_KB":109.13,"real_KB":88.88,"callCount":3,"realCount":1},{"hno":126054,"hnm":"여의나루더명남더블레스","typeNm":"오피스텔","callPrice":2057.44,"realPrice":null,"kbPrice":2046.44,"call_KB":100.53,"real_KB":null,"callCount":3,"realCount":0},{"hno":105605,"hnm":"휴브리지(도시형)","typeNm":"아파트","callPrice":1926.24,"realPrice":null,"kbPrice":1849.69,"call_KB":104.13,"real_KB":null,"callCount":4,"realCount":0},{"hno":106734,"hnm":"훼미리하우스138(도시형)","typeNm":"아파트","callPrice":1851.47,"realPrice":1739.26,"kbPrice":1865.49,"call_KB":99.24,"real_KB":93.23,"callCount":1,"realCount":-1}]