[{"hno":10243,"hnm":"화성그랜드파크","typeNm":"아파트","callPrice":1128.37,"realPrice":1038.3,"kbPrice":1083.71,"call_KB":104.12,"real_KB":95.81,"callCount":47,"realCount":6},{"hno":5205,"hnm":"그린빌2차","typeNm":"아파트","callPrice":847.57,"realPrice":763.23,"kbPrice":784.52,"call_KB":108.03,"real_KB":97.28,"callCount":27,"realCount":11},{"hno":13079,"hnm":"부영5단지","typeNm":"아파트","callPrice":771.77,"realPrice":696.5,"kbPrice":726.09,"call_KB":106.29,"real_KB":95.92,"callCount":29,"realCount":14},{"hno":5207,"hnm":"칠곡금빛타운","typeNm":"아파트","callPrice":769.72,"realPrice":728.67,"kbPrice":764.72,"call_KB":100.65,"real_KB":95.28,"callCount":25,"realCount":4},{"hno":13078,"hnm":"부영7단지","typeNm":"아파트","callPrice":759.14,"realPrice":715.24,"kbPrice":765.4,"call_KB":99.18,"real_KB":93.44,"callCount":29,"realCount":16},{"hno":13978,"hnm":"부영6단지","typeNm":"아파트","callPrice":745.59,"realPrice":702.99,"kbPrice":770.42,"call_KB":96.77,"real_KB":91.24,"callCount":30,"realCount":10},{"hno":25565,"hnm":"부영3단지","typeNm":"아파트","callPrice":743.19,"realPrice":725.84,"kbPrice":760.24,"call_KB":97.75,"real_KB":95.47,"callCount":38,"realCount":11},{"hno":5217,"hnm":"칠곡미래타운","typeNm":"아파트","callPrice":737.34,"realPrice":726.06,"kbPrice":752.85,"call_KB":97.93,"real_KB":96.44,"callCount":31,"realCount":3},{"hno":5225,"hnm":"칠곡서한타운3차","typeNm":"아파트","callPrice":730.74,"realPrice":643.46,"kbPrice":720.39,"call_KB":101.43,"real_KB":89.32,"callCount":11,"realCount":7},{"hno":25837,"hnm":"그린빌4단지","typeNm":"아파트","callPrice":708.94,"realPrice":699.7,"kbPrice":730.61,"call_KB":97.03,"real_KB":95.76,"callCount":46,"realCount":7},{"hno":23734,"hnm":"그린빌3차","typeNm":"아파트","callPrice":689.04,"realPrice":657.45,"kbPrice":688.19,"call_KB":100.12,"real_KB":95.53,"callCount":47,"realCount":15},{"hno":5230,"hnm":"칠곡한라타운2차","typeNm":"아파트","callPrice":678.36,"realPrice":655.76,"kbPrice":679.15,"call_KB":99.88,"real_KB":96.55,"callCount":32,"realCount":10},{"hno":5222,"hnm":"칠곡청구타운","typeNm":"아파트","callPrice":672.89,"realPrice":684.19,"kbPrice":680.47,"call_KB":98.88,"real_KB":100.54,"callCount":25,"realCount":4},{"hno":5209,"hnm":"칠곡동서영남","typeNm":"아파트","callPrice":668.69,"realPrice":649.75,"kbPrice":664.14,"call_KB":100.68,"real_KB":97.83,"callCount":33,"realCount":18},{"hno":8068,"hnm":"칠곡건영","typeNm":"아파트","callPrice":653.83,"realPrice":661.46,"kbPrice":640.07,"call_KB":102.14,"real_KB":103.34,"callCount":12,"realCount":4},{"hno":5212,"hnm":"칠곡동서타운2차","typeNm":"아파트","callPrice":597.97,"realPrice":603.52,"kbPrice":601.09,"call_KB":99.48,"real_KB":100.4,"callCount":18,"realCount":4}]