[{"hno":108340,"hnm":"상무SK뷰","typeNm":"아파트","callPrice":2200.48,"realPrice":1961.56,"kbPrice":1961.08,"call_KB":112.2,"real_KB":100.02,"callCount":28,"realCount":8},{"hno":5529,"hnm":"금호쌍용","typeNm":"아파트","callPrice":1712.14,"realPrice":1560.37,"kbPrice":1544.61,"call_KB":110.84,"real_KB":101.01,"callCount":31,"realCount":8},{"hno":5535,"hnm":"중흥1차","typeNm":"아파트","callPrice":1579.33,"realPrice":1332.58,"kbPrice":1349.79,"call_KB":117,"real_KB":98.72,"callCount":18,"realCount":6},{"hno":102765,"hnm":"갤러리303","typeNm":"아파트","callPrice":1541.25,"realPrice":1346.97,"kbPrice":1436.86,"call_KB":107.26,"real_KB":93.74,"callCount":25,"realCount":1},{"hno":119335,"hnm":"상무지구영무예다음(주상복합)","typeNm":"아파트","callPrice":1494.53,"realPrice":1350.76,"kbPrice":1340.23,"call_KB":111.51,"real_KB":100.78,"callCount":24,"realCount":1},{"hno":108838,"hnm":"상무광명메이루즈(주상복합)","typeNm":"아파트","callPrice":1477.56,"realPrice":1333.16,"kbPrice":1349.51,"call_KB":109.48,"real_KB":98.78,"callCount":47,"realCount":4},{"hno":8100,"hnm":"금호타운3차","typeNm":"아파트","callPrice":1411.3,"realPrice":1279.16,"kbPrice":1352.82,"call_KB":104.32,"real_KB":94.55,"callCount":22,"realCount":6},{"hno":5547,"hnm":"현대","typeNm":"아파트","callPrice":1409.6,"realPrice":1239.08,"kbPrice":1157.69,"call_KB":121.76,"real_KB":107.03,"callCount":23,"realCount":1},{"hno":5537,"hnm":"중흥2단지","typeNm":"아파트","callPrice":1350.62,"realPrice":1205.28,"kbPrice":1207.94,"call_KB":111.81,"real_KB":99.78,"callCount":43,"realCount":11},{"hno":5545,"hnm":"라인대주","typeNm":"아파트","callPrice":1214.72,"realPrice":1066.3,"kbPrice":1084.55,"call_KB":112,"real_KB":98.31,"callCount":45,"realCount":18},{"hno":5542,"hnm":"금호타운4차","typeNm":"아파트","callPrice":1192.13,"realPrice":1106.57,"kbPrice":1121.29,"call_KB":106.31,"real_KB":98.68,"callCount":28,"realCount":7},{"hno":5544,"hnm":"대주","typeNm":"아파트","callPrice":993.25,"realPrice":938.17,"kbPrice":853.47,"call_KB":116.37,"real_KB":109.92,"callCount":12,"realCount":8},{"hno":5532,"hnm":"금호대우","typeNm":"아파트","callPrice":986.48,"realPrice":922.72,"kbPrice":932.97,"call_KB":105.73,"real_KB":98.9,"callCount":54,"realCount":20},{"hno":5533,"hnm":"상무지구라인,동산","typeNm":"아파트","callPrice":984.77,"realPrice":974.16,"kbPrice":1089.77,"call_KB":90.36,"real_KB":89.39,"callCount":29,"realCount":17},{"hno":5539,"hnm":"한국","typeNm":"아파트","callPrice":969.16,"realPrice":847.11,"kbPrice":911.58,"call_KB":106.31,"real_KB":92.92,"callCount":22,"realCount":9},{"hno":5541,"hnm":"해광한신","typeNm":"아파트","callPrice":961.33,"realPrice":775.38,"kbPrice":860.38,"call_KB":111.73,"real_KB":90.12,"callCount":17,"realCount":8},{"hno":16693,"hnm":"호반","typeNm":"아파트","callPrice":892.7,"realPrice":792.5,"kbPrice":822.18,"call_KB":108.57,"real_KB":96.39,"callCount":12,"realCount":10},{"hno":107238,"hnm":"치평로잔티움파크","typeNm":"오피스텔","callPrice":768.96,"realPrice":740.22,"kbPrice":704.31,"call_KB":109.17,"real_KB":105.09,"callCount":14,"realCount":2},{"hno":16691,"hnm":"상무우미","typeNm":"아파트","callPrice":767.09,"realPrice":679.45,"kbPrice":712.8,"call_KB":107.61,"real_KB":95.32,"callCount":37,"realCount":10},{"hno":112366,"hnm":"상무e-다움골드(도시형)","typeNm":"아파트","callPrice":708.3,"realPrice":518.77,"kbPrice":702.99,"call_KB":100.75,"real_KB":73.79,"callCount":7,"realCount":0},{"hno":104529,"hnm":"중흥S-클래스스카이31","typeNm":"오피스텔","callPrice":608.26,"realPrice":559.64,"kbPrice":617,"call_KB":98.58,"real_KB":90.7,"callCount":13,"realCount":6},{"hno":110684,"hnm":"유탑유블레스트윈시티","typeNm":"오피스텔","callPrice":600.63,"realPrice":531.11,"kbPrice":574.51,"call_KB":104.54,"real_KB":92.44,"callCount":21,"realCount":1},{"hno":113064,"hnm":"센트럴시티","typeNm":"오피스텔","callPrice":581.18,"realPrice":559.87,"kbPrice":556.02,"call_KB":104.52,"real_KB":100.69,"callCount":14,"realCount":0},{"hno":111985,"hnm":"상무리채2","typeNm":"오피스텔","callPrice":549.7,"realPrice":420.02,"kbPrice":549.16,"call_KB":100.09,"real_KB":76.48,"callCount":1,"realCount":1},{"hno":108202,"hnm":"상무리채1","typeNm":"오피스텔","callPrice":471.64,"realPrice":367.07,"kbPrice":459.51,"call_KB":102.64,"real_KB":79.88,"callCount":5,"realCount":1},{"hno":19360,"hnm":"광주대우디오빌","typeNm":"오피스텔","callPrice":471.59,"realPrice":473.59,"kbPrice":421.96,"call_KB":111.76,"real_KB":112.23,"callCount":17,"realCount":5},{"hno":18031,"hnm":"랜드피아","typeNm":"오피스텔","callPrice":370.38,"realPrice":352.88,"kbPrice":376.01,"call_KB":98.5,"real_KB":93.84,"callCount":3,"realCount":4}]