[{"hno":117833,"hnm":"사천KCC스위첸","typeNm":"아파트","callPrice":896.71,"realPrice":null,"kbPrice":859.49,"call_KB":104.32,"real_KB":null,"callCount":90,"realCount":0},{"hno":100811,"hnm":"대영풀리비안","typeNm":"아파트","callPrice":727.59,"realPrice":557.7,"kbPrice":586.66,"call_KB":124.02,"real_KB":95.06,"callCount":1,"realCount":2},{"hno":19213,"hnm":"HK명가","typeNm":"아파트","callPrice":519.36,"realPrice":529.64,"kbPrice":524.67,"call_KB":98.98,"real_KB":100.94,"callCount":1,"realCount":1},{"hno":15601,"hnm":"사천청구타운","typeNm":"아파트","callPrice":518.42,"realPrice":439.47,"kbPrice":466.02,"call_KB":111.24,"real_KB":94.3,"callCount":9,"realCount":7},{"hno":109955,"hnm":"토산아델리움","typeNm":"아파트","callPrice":454.57,"realPrice":null,"kbPrice":445.32,"call_KB":102.07,"real_KB":null,"callCount":10,"realCount":0},{"hno":6973,"hnm":"사천한보3차","typeNm":"아파트","callPrice":451.69,"realPrice":405.11,"kbPrice":444.23,"call_KB":101.68,"real_KB":91.19,"callCount":4,"realCount":7},{"hno":102776,"hnm":"삼성","typeNm":"아파트","callPrice":384.19,"realPrice":352.65,"kbPrice":382.71,"call_KB":100.38,"real_KB":92.14,"callCount":14,"realCount":13},{"hno":100817,"hnm":"재성햇살채","typeNm":"아파트","callPrice":374.66,"realPrice":364.4,"kbPrice":348.31,"call_KB":107.56,"real_KB":104.61,"callCount":1,"realCount":1},{"hno":6971,"hnm":"대흥그랜저맨션","typeNm":"아파트","callPrice":371.6,"realPrice":null,"kbPrice":373.79,"call_KB":99.41,"real_KB":null,"callCount":3,"realCount":0},{"hno":100813,"hnm":"송보파인빌","typeNm":"아파트","callPrice":327.79,"realPrice":293.33,"kbPrice":296.15,"call_KB":110.68,"real_KB":99.04,"callCount":30,"realCount":21},{"hno":15603,"hnm":"사천한보훼미리타운","typeNm":"아파트","callPrice":317.77,"realPrice":301.4,"kbPrice":330.76,"call_KB":96.07,"real_KB":91.12,"callCount":14,"realCount":4},{"hno":6974,"hnm":"한빛타운","typeNm":"아파트","callPrice":295.54,"realPrice":237,"kbPrice":272.72,"call_KB":108.36,"real_KB":86.9,"callCount":2,"realCount":5},{"hno":15602,"hnm":"한보맨션","typeNm":"아파트","callPrice":232.49,"realPrice":250.19,"kbPrice":301.17,"call_KB":77.19,"real_KB":83.07,"callCount":4,"realCount":2},{"hno":16660,"hnm":"유정2차","typeNm":"아파트","callPrice":200.91,"realPrice":175.79,"kbPrice":276.25,"call_KB":72.72,"real_KB":63.63,"callCount":1,"realCount":1}]