[{"hno":105118,"hnm":"지평더웰II","typeNm":"아파트","callPrice":758.82,"realPrice":726.84,"kbPrice":583.5,"call_KB":130.04,"real_KB":124.56,"callCount":"1","realCount":"3"},{"hno":26532,"hnm":"영동설계주공","typeNm":"아파트","callPrice":378.15,"realPrice":352.11,"kbPrice":349.05,"call_KB":108.33,"real_KB":100.87,"callCount":"2","realCount":"15"},{"hno":114970,"hnm":"금강","typeNm":"아파트","callPrice":253.14,"realPrice":260.43,"kbPrice":305.98,"call_KB":82.73,"real_KB":85.11,"callCount":"3","realCount":"9"},{"hno":15318,"hnm":"삼부","typeNm":"아파트","callPrice":null,"realPrice":192.73,"kbPrice":210.23,"call_KB":null,"real_KB":91.67,"callCount":null,"realCount":"5"},{"hno":100975,"hnm":"서한감고을","typeNm":"아파트","callPrice":null,"realPrice":525.08,"kbPrice":466.74,"call_KB":null,"real_KB":112.5,"callCount":null,"realCount":"1"},{"hno":15319,"hnm":"영동현대","typeNm":"아파트","callPrice":null,"realPrice":486.27,"kbPrice":440.9,"call_KB":null,"real_KB":110.28,"callCount":null,"realCount":"1"},{"hno":102180,"hnm":"영동미드림","typeNm":"아파트","callPrice":null,"realPrice":475.88,"kbPrice":464.08,"call_KB":null,"real_KB":102.54,"callCount":null,"realCount":"4"},{"hno":116621,"hnm":"영동이원리버빌","typeNm":"아파트","callPrice":null,"realPrice":686.05,"kbPrice":646.06,"call_KB":null,"real_KB":106.19,"callCount":null,"realCount":"1"},{"hno":10688,"hnm":"조한드림플러스","typeNm":"아파트","callPrice":null,"realPrice":514.61,"kbPrice":428.84,"call_KB":null,"real_KB":120,"callCount":null,"realCount":"1"}]