[{"hno":105039,"hnm":"대원칸타빌3차","typeNm":"아파트","callPrice":1565.96,"realPrice":1511.27,"kbPrice":1517.39,"call_KB":103.2,"real_KB":99.59,"callCount":40,"realCount":13},{"hno":102720,"hnm":"대원칸타빌1차","typeNm":"아파트","callPrice":1334.3,"realPrice":1281.13,"kbPrice":1294.33,"call_KB":103.08,"real_KB":98.97,"callCount":39,"realCount":18},{"hno":105322,"hnm":"율량5단지선광로즈웰2차","typeNm":"아파트","callPrice":1209.67,"realPrice":1176.21,"kbPrice":1174.98,"call_KB":102.95,"real_KB":100.1,"callCount":27,"realCount":8}]