[{"hno":110482,"hnm":"우미린에듀파크1단지","typeNm":"아파트","callPrice":1355.9,"realPrice":1307.36,"kbPrice":1254.39,"call_KB":108.09,"real_KB":104.22,"callCount":38,"realCount":9},{"hno":102703,"hnm":"청주용정한라비발디1단지","typeNm":"아파트","callPrice":1129.59,"realPrice":null,"kbPrice":1068.88,"call_KB":105.67,"real_KB":null,"callCount":31,"realCount":0},{"hno":102705,"hnm":"청주용정한라비발디2단지","typeNm":"아파트","callPrice":1115.73,"realPrice":1036.09,"kbPrice":1036.14,"call_KB":107.68,"real_KB":99.99,"callCount":29,"realCount":31},{"hno":13334,"hnm":"하은베스트빌","typeNm":"아파트","callPrice":424.45,"realPrice":459.03,"kbPrice":440.17,"call_KB":96.42,"real_KB":104.28,"callCount":1,"realCount":1}]