[{"hno":101762,"hnm":"해솔마을현진에버빌1단지","typeNm":"아파트","callPrice":2602.97,"realPrice":2350.08,"kbPrice":2211.38,"call_KB":117.7,"real_KB":106.27,"callCount":60,"realCount":9},{"hno":103673,"hnm":"광주수완대방노블랜드6차","typeNm":"아파트","callPrice":2146.24,"realPrice":2141.35,"kbPrice":2001.68,"call_KB":107.22,"real_KB":106.97,"callCount":53,"realCount":3},{"hno":104893,"hnm":"수완진아리채2차","typeNm":"아파트","callPrice":2094.75,"realPrice":1677,"kbPrice":1882.11,"call_KB":111.29,"real_KB":89.1,"callCount":17,"realCount":1},{"hno":27438,"hnm":"광주수완코오롱하늘채","typeNm":"아파트","callPrice":1941.21,"realPrice":1842.85,"kbPrice":1769.63,"call_KB":109.69,"real_KB":104.13,"callCount":80,"realCount":9},{"hno":101250,"hnm":"은빛마을모아엘가","typeNm":"아파트","callPrice":1909.68,"realPrice":1803.1,"kbPrice":1759.2,"call_KB":108.55,"real_KB":102.49,"callCount":40,"realCount":10},{"hno":27893,"hnm":"수완우미린1차","typeNm":"아파트","callPrice":1880.72,"realPrice":1636.88,"kbPrice":1628.67,"call_KB":115.47,"real_KB":100.5,"callCount":12,"realCount":4},{"hno":103310,"hnm":"해솔마을대방노블랜드2차","typeNm":"아파트","callPrice":1877.92,"realPrice":1697.1,"kbPrice":1666.55,"call_KB":112.68,"real_KB":101.83,"callCount":27,"realCount":6},{"hno":102414,"hnm":"수완대주피오레6단지","typeNm":"아파트","callPrice":1757.27,"realPrice":1596.35,"kbPrice":1596.35,"call_KB":110.08,"real_KB":100,"callCount":9,"realCount":1},{"hno":103498,"hnm":"수완지구영무예다음2차","typeNm":"아파트","callPrice":1521.47,"realPrice":1360.51,"kbPrice":1351.77,"call_KB":112.55,"real_KB":100.64,"callCount":23,"realCount":2},{"hno":100460,"hnm":"수완우미린2차","typeNm":"아파트","callPrice":1473.75,"realPrice":1454.41,"kbPrice":1397.76,"call_KB":105.43,"real_KB":104.05,"callCount":49,"realCount":16}]