[{"hno":7661,"hnm":"함양한주","typeNm":"아파트","callPrice":null,"realPrice":670.2,"kbPrice":622.08,"call_KB":null,"real_KB":107.73,"callCount":null,"realCount":5},{"hno":112748,"hnm":"삼정그린코아","typeNm":"아파트","callPrice":null,"realPrice":789.1,"kbPrice":806.42,"call_KB":null,"real_KB":97.85,"callCount":null,"realCount":3},{"hno":16966,"hnm":"한마음","typeNm":"아파트","callPrice":null,"realPrice":445.85,"kbPrice":432.47,"call_KB":null,"real_KB":103.09,"callCount":null,"realCount":1},{"hno":116456,"hnm":"함양웰가센트뷰","typeNm":"아파트","callPrice":null,"realPrice":935.04,"kbPrice":958.15,"call_KB":null,"real_KB":97.58,"callCount":null,"realCount":2},{"hno":112746,"hnm":"상림팰리스","typeNm":"아파트","callPrice":null,"realPrice":759.41,"kbPrice":696.13,"call_KB":null,"real_KB":109.09,"callCount":null,"realCount":1}]