[{"hno":125047,"hnm":"더샵원주센트럴파크1단지","typeNm":"아파트","callPrice":1513.47,"realPrice":1430.41,"kbPrice":1444.72,"call_KB":104.75,"real_KB":99,"callCount":103,"realCount":52},{"hno":107637,"hnm":"무실우미린","typeNm":"아파트","callPrice":1298.68,"realPrice":1226.74,"kbPrice":1253.52,"call_KB":103.6,"real_KB":97.86,"callCount":52,"realCount":11},{"hno":104263,"hnm":"원주무실세영리첼1차","typeNm":"아파트","callPrice":1289.41,"realPrice":1139.47,"kbPrice":1169.39,"call_KB":110.26,"real_KB":97.44,"callCount":28,"realCount":12},{"hno":105372,"hnm":"원주무실세영리첼2차","typeNm":"아파트","callPrice":1231.78,"realPrice":1153.21,"kbPrice":1145.1,"call_KB":107.56,"real_KB":100.7,"callCount":39,"realCount":15},{"hno":27440,"hnm":"무실e-편한세상","typeNm":"아파트","callPrice":1125.56,"realPrice":1047.42,"kbPrice":1085.36,"call_KB":103.7,"real_KB":96.5,"callCount":49,"realCount":10},{"hno":102138,"hnm":"원주무실휴먼시아6단지","typeNm":"아파트","callPrice":951.25,"realPrice":892.46,"kbPrice":922.68,"call_KB":103.09,"real_KB":96.72,"callCount":38,"realCount":21},{"hno":13710,"hnm":"요진보네르카운티","typeNm":"아파트","callPrice":872.4,"realPrice":833.1,"kbPrice":866.66,"call_KB":100.66,"real_KB":96.12,"callCount":41,"realCount":12},{"hno":100442,"hnm":"무실주공3단지","typeNm":"아파트","callPrice":828.9,"realPrice":808.04,"kbPrice":789.93,"call_KB":104.93,"real_KB":102.29,"callCount":46,"realCount":27},{"hno":22210,"hnm":"뜨란채","typeNm":"아파트","callPrice":805.32,"realPrice":787.96,"kbPrice":824.17,"call_KB":97.71,"real_KB":95.6,"callCount":31,"realCount":10},{"hno":25860,"hnm":"무실주공4단지","typeNm":"아파트","callPrice":773.44,"realPrice":725.36,"kbPrice":748.2,"call_KB":103.37,"real_KB":96.94,"callCount":25,"realCount":21},{"hno":116812,"hnm":"원주무실코아루허브288","typeNm":"오피스텔","callPrice":579.12,"realPrice":538.82,"kbPrice":534.19,"call_KB":108.41,"real_KB":100.86,"callCount":22,"realCount":2},{"hno":127232,"hnm":"엠시티","typeNm":"오피스텔","callPrice":527.55,"realPrice":509.87,"kbPrice":587.82,"call_KB":89.74,"real_KB":86.73,"callCount":4,"realCount":4}]