[{"hno":25784,"hnm":"광명두산위브트레지움","typeNm":"아파트","callPrice":2994.66,"realPrice":2874.27,"kbPrice":2766.51,"call_KB":108.24,"real_KB":103.89,"callCount":38,"realCount":35},{"hno":25937,"hnm":"e편한세상센트레빌","typeNm":"아파트","callPrice":2908.93,"realPrice":2734.13,"kbPrice":2697.84,"call_KB":107.82,"real_KB":101.34,"callCount":106,"realCount":65},{"hno":1625,"hnm":"주공12단지","typeNm":"아파트","callPrice":2796.24,"realPrice":2519.61,"kbPrice":2567.09,"call_KB":108.92,"real_KB":98.15,"callCount":77,"realCount":36},{"hno":1631,"hnm":"주공6단지","typeNm":"아파트","callPrice":2496.59,"realPrice":2277.3,"kbPrice":2330.01,"call_KB":107.14,"real_KB":97.73,"callCount":38,"realCount":8},{"hno":1624,"hnm":"주공11단지","typeNm":"아파트","callPrice":2476.47,"realPrice":2330.48,"kbPrice":2441.18,"call_KB":101.44,"real_KB":95.46,"callCount":36,"realCount":15},{"hno":1628,"hnm":"주공3단지","typeNm":"아파트","callPrice":2466.8,"realPrice":2140.43,"kbPrice":2158.52,"call_KB":114.28,"real_KB":99.16,"callCount":88,"realCount":31},{"hno":1635,"hnm":"주공8단지","typeNm":"아파트","callPrice":2397.62,"realPrice":2227.2,"kbPrice":2252.99,"call_KB":106.41,"real_KB":98.85,"callCount":54,"realCount":13},{"hno":1629,"hnm":"주공4단지","typeNm":"아파트","callPrice":2385.61,"realPrice":2135.5,"kbPrice":2180.72,"call_KB":109.39,"real_KB":97.92,"callCount":30,"realCount":15},{"hno":1636,"hnm":"주공9단지","typeNm":"아파트","callPrice":2371.89,"realPrice":2141.34,"kbPrice":2158.91,"call_KB":109.86,"real_KB":99.18,"callCount":50,"realCount":20},{"hno":1632,"hnm":"주공7단지","typeNm":"아파트","callPrice":2364.18,"realPrice":2198.8,"kbPrice":2212.55,"call_KB":106.85,"real_KB":99.37,"callCount":25,"realCount":18},{"hno":1623,"hnm":"주공10단지","typeNm":"아파트","callPrice":2354.27,"realPrice":2170.13,"kbPrice":2177.35,"call_KB":108.12,"real_KB":99.66,"callCount":76,"realCount":38},{"hno":1627,"hnm":"주공1단지","typeNm":"아파트","callPrice":2335.26,"realPrice":2071.2,"kbPrice":2105.03,"call_KB":110.93,"real_KB":98.39,"callCount":60,"realCount":34},{"hno":1626,"hnm":"주공2단지","typeNm":"아파트","callPrice":2309.16,"realPrice":2125.37,"kbPrice":2113.28,"call_KB":109.26,"real_KB":100.57,"callCount":34,"realCount":10},{"hno":1630,"hnm":"주공5단지","typeNm":"아파트","callPrice":2061.84,"realPrice":1912.61,"kbPrice":1941.74,"call_KB":106.18,"real_KB":98.49,"callCount":48,"realCount":37},{"hno":100395,"hnm":"광명하안현대1,2단지","typeNm":"아파트","callPrice":1787.46,"realPrice":1675.1,"kbPrice":1839.68,"call_KB":97.16,"real_KB":91.05,"callCount":19,"realCount":5},{"hno":18303,"hnm":"녹원토피아","typeNm":"오피스텔","callPrice":683.56,"realPrice":503.88,"kbPrice":659.59,"call_KB":103.63,"real_KB":76.39,"callCount":4,"realCount":-1}]