[{"hno":5710,"hnm":"한숲","typeNm":"아파트","callPrice":1003.95,"realPrice":903.24,"kbPrice":953.03,"call_KB":105.34,"real_KB":94.77,"callCount":43,"realCount":9},{"hno":5698,"hnm":"신동아","typeNm":"아파트","callPrice":761.98,"realPrice":735.15,"kbPrice":759.6,"call_KB":100.31,"real_KB":96.78,"callCount":30,"realCount":8},{"hno":5709,"hnm":"새피앙","typeNm":"아파트","callPrice":732.75,"realPrice":734.96,"kbPrice":639.26,"call_KB":114.62,"real_KB":114.97,"callCount":9,"realCount":0},{"hno":26446,"hnm":"푸른","typeNm":"아파트","callPrice":706.25,"realPrice":649.38,"kbPrice":638.2,"call_KB":110.66,"real_KB":101.75,"callCount":20,"realCount":5},{"hno":101995,"hnm":"부성한울","typeNm":"아파트","callPrice":597.75,"realPrice":565.86,"kbPrice":513.67,"call_KB":116.36,"real_KB":110.16,"callCount":4,"realCount":3},{"hno":103807,"hnm":"큰솔2단지","typeNm":"아파트","callPrice":517.4,"realPrice":491.15,"kbPrice":483.62,"call_KB":106.98,"real_KB":101.55,"callCount":9,"realCount":5},{"hno":10542,"hnm":"신진크로바맨션","typeNm":"아파트","callPrice":480.92,"realPrice":456.39,"kbPrice":398.89,"call_KB":120.56,"real_KB":114.41,"callCount":2,"realCount":2},{"hno":103804,"hnm":"큰솔1단지","typeNm":"아파트","callPrice":445.41,"realPrice":459.4,"kbPrice":426.62,"call_KB":104.4,"real_KB":107.68,"callCount":8,"realCount":6}]