[{"sno":3611010700,"snm":"나성동","callPrice":2538.81,"realPrice":2280.5,"kbPrice":2295.05,"call_KB":110.62,"real_KB":99.36,"callCount":258,"realCount":53},{"sno":3611010800,"snm":"새롬동","callPrice":2357.51,"realPrice":2083.86,"kbPrice":2198.89,"call_KB":107.21,"real_KB":94.76,"callCount":514,"realCount":125},{"sno":3611010300,"snm":"보람동","callPrice":2163.42,"realPrice":1954.93,"kbPrice":2002.56,"call_KB":108.03,"real_KB":97.62,"callCount":485,"realCount":93},{"sno":3611011600,"snm":"해밀동","callPrice":2146.41,"realPrice":1878.17,"kbPrice":1916.48,"call_KB":111.99,"real_KB":98,"callCount":201,"realCount":23},{"sno":3611010100,"snm":"반곡동","callPrice":2145.92,"realPrice":1745.66,"kbPrice":1875.97,"call_KB":114.38,"real_KB":93.05,"callCount":334,"realCount":99},{"sno":3611010200,"snm":"소담동","callPrice":2037.33,"realPrice":1836.27,"kbPrice":1859.65,"call_KB":109.55,"real_KB":98.74,"callCount":483,"realCount":158},{"sno":3611010400,"snm":"대평동","callPrice":2014.49,"realPrice":1835.96,"kbPrice":1833.45,"call_KB":109.87,"real_KB":100.13,"callCount":234,"realCount":24},{"sno":3611010900,"snm":"다정동","callPrice":2009.65,"realPrice":1809.19,"kbPrice":1823.93,"call_KB":110.18,"real_KB":99.19,"callCount":609,"realCount":133},{"sno":3611011000,"snm":"어진동","callPrice":1850.75,"realPrice":1487.6,"kbPrice":1621.19,"call_KB":114.15,"real_KB":91.75,"callCount":189,"realCount":61},{"sno":3611011400,"snm":"도담동","callPrice":1819.62,"realPrice":1722.41,"kbPrice":1684.9,"call_KB":107.99,"real_KB":102.22,"callCount":592,"realCount":124},{"sno":3611011800,"snm":"집현동","callPrice":1786.62,"realPrice":1698.69,"kbPrice":1716.54,"call_KB":104.08,"real_KB":98.96,"callCount":157,"realCount":42},{"sno":3611010600,"snm":"한솔동","callPrice":1753.7,"realPrice":1429.05,"kbPrice":1602.61,"call_KB":109.42,"real_KB":89.17,"callCount":677,"realCount":78},{"sno":3611011100,"snm":"종촌동","callPrice":1616.39,"realPrice":1496.93,"kbPrice":1516.96,"call_KB":106.55,"real_KB":98.67,"callCount":510,"realCount":116},{"sno":3611011300,"snm":"아름동","callPrice":1590.91,"realPrice":1425.22,"kbPrice":1483.67,"call_KB":107.22,"real_KB":96.06,"callCount":399,"realCount":95},{"sno":3611011200,"snm":"고운동","callPrice":1577.58,"realPrice":1331.89,"kbPrice":1406.71,"call_KB":112.14,"real_KB":94.68,"callCount":923,"realCount":167},{"sno":3611034000,"snm":"금남면","callPrice":1044.28,"realPrice":994.84,"kbPrice":997.47,"call_KB":104.69,"real_KB":99.73,"callCount":53,"realCount":12},{"sno":3611036000,"snm":"연서면","callPrice":788.42,"realPrice":747.87,"kbPrice":801.45,"call_KB":98.37,"real_KB":93.31,"callCount":19,"realCount":4},{"sno":3611025000,"snm":"조치원읍","callPrice":731.96,"realPrice":689.8,"kbPrice":716.07,"call_KB":102.21,"real_KB":96.33,"callCount":492,"realCount":111},{"sno":3611032000,"snm":"연동면","callPrice":724.85,"realPrice":582.43,"kbPrice":625.54,"call_KB":115.87,"real_KB":93.1,"callCount":30,"realCount":5},{"sno":3611033000,"snm":"부강면","callPrice":578.85,"realPrice":581.21,"kbPrice":526.35,"call_KB":109.97,"real_KB":110.42,"callCount":7,"realCount":5},{"sno":3611037000,"snm":"전의면","callPrice":399.78,"realPrice":380.43,"kbPrice":350.83,"call_KB":113.95,"real_KB":108.43,"callCount":43,"realCount":12}]