[{"hno":117765,"hnm":"원주롯데캐슬골드파크2차","typeNm":"아파트","callPrice":1326.35,"realPrice":1212.51,"kbPrice":1176.45,"call_KB":112.74,"real_KB":103.06,"callCount":38,"realCount":13},{"hno":117764,"hnm":"원주롯데캐슬골드파크1차","typeNm":"아파트","callPrice":1296.21,"realPrice":1144.91,"kbPrice":1174.55,"call_KB":110.35,"real_KB":97.47,"callCount":41,"realCount":10},{"hno":111850,"hnm":"원주롯데캐슬더퍼스트2차","typeNm":"아파트","callPrice":1051.9,"realPrice":1001.92,"kbPrice":958.51,"call_KB":109.74,"real_KB":104.52,"callCount":97,"realCount":23},{"hno":111403,"hnm":"원주롯데캐슬더퍼스트","typeNm":"아파트","callPrice":1003.77,"realPrice":915.5,"kbPrice":923.13,"call_KB":108.73,"real_KB":99.17,"callCount":79,"realCount":33},{"hno":118527,"hnm":"원주기업도시유보라아이비파크2단지","typeNm":"아파트","callPrice":1002.98,"realPrice":933.04,"kbPrice":937.29,"call_KB":107,"real_KB":99.54,"callCount":58,"realCount":10},{"hno":114283,"hnm":"원주기업도시호반베르디움(3-2블록)","typeNm":"아파트","callPrice":989.35,"realPrice":939.95,"kbPrice":935.05,"call_KB":105.8,"real_KB":100.52,"callCount":55,"realCount":17},{"hno":113162,"hnm":"원주기업도시라온프라이빗","typeNm":"아파트","callPrice":988.12,"realPrice":905.58,"kbPrice":935.8,"call_KB":105.59,"real_KB":96.77,"callCount":73,"realCount":18},{"hno":118431,"hnm":"원주기업도시유보라아이비파크1단지","typeNm":"아파트","callPrice":978.48,"realPrice":911.36,"kbPrice":942.5,"call_KB":103.81,"real_KB":96.69,"callCount":28,"realCount":5},{"hno":120519,"hnm":"이지더원더그레이스","typeNm":"아파트","callPrice":972.91,"realPrice":925.5,"kbPrice":931.29,"call_KB":104.46,"real_KB":99.37,"callCount":52,"realCount":25},{"hno":114282,"hnm":"원주기업도시호반베르디움(3-1블록)","typeNm":"아파트","callPrice":968.61,"realPrice":934.48,"kbPrice":937.02,"call_KB":103.37,"real_KB":99.72,"callCount":59,"realCount":21},{"hno":114284,"hnm":"이지더원1차","typeNm":"아파트","callPrice":964.97,"realPrice":848.56,"kbPrice":901.32,"call_KB":107.06,"real_KB":94.14,"callCount":105,"realCount":28},{"hno":111661,"hnm":"원주기업도시호반베르디움8단지","typeNm":"아파트","callPrice":945.46,"realPrice":906.89,"kbPrice":917.49,"call_KB":103.04,"real_KB":98.84,"callCount":64,"realCount":27}]