[{"hno":19740,"hnm":"트리비앙","typeNm":"아파트","callPrice":1756.38,"realPrice":1688.56,"kbPrice":1647.12,"call_KB":106.63,"real_KB":102.51,"callCount":"141","realCount":"73"},{"hno":25168,"hnm":"노블파크","typeNm":"아파트","callPrice":1676.26,"realPrice":1569.07,"kbPrice":1570.21,"call_KB":106.75,"real_KB":99.92,"callCount":"151","realCount":"54"},{"hno":7743,"hnm":"현대","typeNm":"아파트","callPrice":1369.19,"realPrice":1234.25,"kbPrice":1257.14,"call_KB":108.91,"real_KB":98.17,"callCount":"57","realCount":"14"},{"hno":100902,"hnm":"현대2차","typeNm":"아파트","callPrice":1367.49,"realPrice":1279.56,"kbPrice":1246.1,"call_KB":109.74,"real_KB":102.68,"callCount":"75","realCount":"20"},{"hno":15778,"hnm":"반림럭키","typeNm":"아파트","callPrice":1079.81,"realPrice":1019.15,"kbPrice":1010.9,"call_KB":106.81,"real_KB":100.81,"callCount":"50","realCount":"16"}]