[{"hno":107032,"hnm":"양학산KCC스위첸","typeNm":"아파트","callPrice":913.18,"realPrice":882.94,"kbPrice":903.99,"call_KB":101.01,"real_KB":97.67,"callCount":"67","realCount":"10"},{"hno":7209,"hnm":"현대1차","typeNm":"아파트","callPrice":454.64,"realPrice":394.59,"kbPrice":371.55,"call_KB":122.36,"real_KB":106.2,"callCount":"2","realCount":"9"},{"hno":13976,"hnm":"용흥현대타워2차","typeNm":"아파트","callPrice":452.16,"realPrice":433.73,"kbPrice":481.06,"call_KB":93.99,"real_KB":90.16,"callCount":"1","realCount":"6"},{"hno":16388,"hnm":"용흥보성타운","typeNm":"아파트","callPrice":415.98,"realPrice":394.41,"kbPrice":400.57,"call_KB":103.84,"real_KB":98.46,"callCount":"1","realCount":"4"},{"hno":7144,"hnm":"용흥쌍용","typeNm":"아파트","callPrice":413.57,"realPrice":414.31,"kbPrice":398.47,"call_KB":103.78,"real_KB":103.97,"callCount":"7","realCount":"7"},{"hno":7185,"hnm":"우방타운","typeNm":"아파트","callPrice":376.6,"realPrice":352.65,"kbPrice":357.4,"call_KB":105.37,"real_KB":98.66,"callCount":"27","realCount":"45"},{"hno":7155,"hnm":"용흥삼성푸른","typeNm":"아파트","callPrice":373.73,"realPrice":356.07,"kbPrice":411.67,"call_KB":90.78,"real_KB":86.49,"callCount":"5","realCount":"5"},{"hno":16391,"hnm":"제일프리미엄타운","typeNm":"아파트","callPrice":370.23,"realPrice":291.97,"kbPrice":321.56,"call_KB":115.13,"real_KB":90.79,"callCount":"2","realCount":"2"},{"hno":16389,"hnm":"성봉우미타운","typeNm":"아파트","callPrice":364.45,"realPrice":258.61,"kbPrice":298.83,"call_KB":121.96,"real_KB":86.54,"callCount":"1","realCount":"2"},{"hno":16396,"hnm":"해원하나로타운2차","typeNm":"아파트","callPrice":322.65,"realPrice":381.84,"kbPrice":348.98,"call_KB":92.45,"real_KB":109.41,"callCount":"1","realCount":"1"},{"hno":16394,"hnm":"하나로타운1차","typeNm":"아파트","callPrice":311.94,"realPrice":293.06,"kbPrice":308.54,"call_KB":101.1,"real_KB":94.98,"callCount":"5","realCount":"5"},{"hno":7204,"hnm":"한라타워맨션","typeNm":"아파트","callPrice":309.48,"realPrice":312.19,"kbPrice":330.73,"call_KB":93.57,"real_KB":94.39,"callCount":"3","realCount":"4"},{"hno":16397,"hnm":"한라전원2차","typeNm":"아파트","callPrice":277.81,"realPrice":288.31,"kbPrice":336.47,"call_KB":82.56,"real_KB":85.68,"callCount":"1","realCount":"3"},{"hno":108880,"hnm":"한라파크7차","typeNm":"아파트","callPrice":255.7,"realPrice":null,"kbPrice":241.34,"call_KB":105.94,"real_KB":null,"callCount":"2","realCount":"0"},{"hno":101135,"hnm":"한라파크6차","typeNm":"아파트","callPrice":189.43,"realPrice":245.68,"kbPrice":250.19,"call_KB":75.71,"real_KB":98.19,"callCount":"2","realCount":"6"},{"hno":16398,"hnm":"한라전원","typeNm":"아파트","callPrice":null,"realPrice":340.87,"kbPrice":346.2,"call_KB":null,"real_KB":98.46,"callCount":null,"realCount":"1"}]