[{"hno":104324,"hnm":"동산마을호반베르디움22단지","typeNm":"아파트","callPrice":2375.39,"realPrice":2140.44,"kbPrice":2178.25,"call_KB":109.05,"real_KB":98.26,"callCount":48,"realCount":16},{"hno":104326,"hnm":"동산마을호반베르디움21단지","typeNm":"아파트","callPrice":2042.02,"realPrice":1948.08,"kbPrice":1949.8,"call_KB":104.72,"real_KB":99.91,"callCount":23,"realCount":7},{"hno":113469,"hnm":"e편한세상시티삼송2차","typeNm":"오피스텔","callPrice":1435.13,"realPrice":1188.07,"kbPrice":1388.88,"call_KB":103.32,"real_KB":85.54,"callCount":52,"realCount":1},{"hno":111316,"hnm":"e편한세상시티삼송","typeNm":"오피스텔","callPrice":1412.22,"realPrice":null,"kbPrice":1350.73,"call_KB":104.55,"real_KB":null,"callCount":52,"realCount":0},{"hno":114375,"hnm":"e편한세상시티삼송3차","typeNm":"오피스텔","callPrice":1389.64,"realPrice":1274.03,"kbPrice":1297.98,"call_KB":107.06,"real_KB":98.15,"callCount":92,"realCount":3}]