[{"hno":100500,"hnm":"경희궁의아침3단지(주상복합)","typeNm":"아파트","callPrice":4955.8,"realPrice":null,"kbPrice":4512.74,"call_KB":109.81,"real_KB":null,"callCount":"4","realCount":"0"},{"hno":20250,"hnm":"파크팰리스(주상복합)","typeNm":"아파트","callPrice":4227.78,"realPrice":null,"kbPrice":3274.13,"call_KB":129.12,"real_KB":null,"callCount":"7","realCount":"0"},{"hno":12545,"hnm":"경희궁의아침2단지","typeNm":"오피스텔","callPrice":1670.75,"realPrice":1702.57,"kbPrice":1608.91,"call_KB":103.84,"real_KB":105.82,"callCount":"9","realCount":"7"},{"hno":12546,"hnm":"광화문시대","typeNm":"오피스텔","callPrice":1575.39,"realPrice":1494.27,"kbPrice":1451.66,"call_KB":108.52,"real_KB":102.93,"callCount":"6","realCount":"4"},{"hno":12547,"hnm":"용비어천가","typeNm":"오피스텔","callPrice":1468.59,"realPrice":1292.38,"kbPrice":1374.49,"call_KB":106.84,"real_KB":94.02,"callCount":"14","realCount":"11"},{"hno":12239,"hnm":"경희궁의아침2단지(주상복합)","typeNm":"아파트","callPrice":null,"realPrice":4668.93,"kbPrice":4470.69,"call_KB":null,"real_KB":104.43,"callCount":null,"realCount":"2"}]