[{"sno":2629010700,"snm":"용호동","callPrice":1680.03,"realPrice":1648.1,"kbPrice":1611.57,"call_KB":104.24,"real_KB":102.26,"callCount":"1395","realCount":"228"},{"sno":2629010600,"snm":"대연동","callPrice":1459.29,"realPrice":1440.96,"kbPrice":1369.17,"call_KB":106.58,"real_KB":105.24,"callCount":"1598","realCount":"336"},{"sno":2629010900,"snm":"문현동","callPrice":1148.77,"realPrice":1152.29,"kbPrice":1102.14,"call_KB":104.23,"real_KB":104.55,"callCount":"743","realCount":"85"},{"sno":2629011000,"snm":"우암동","callPrice":918.1,"realPrice":841.33,"kbPrice":841.63,"call_KB":109.08,"real_KB":99.96,"callCount":"217","realCount":"18"},{"sno":2629010800,"snm":"용당동","callPrice":803.77,"realPrice":686.92,"kbPrice":798.84,"call_KB":100.61,"real_KB":85.99,"callCount":"155","realCount":"14"},{"sno":2629011100,"snm":"감만동","callPrice":790.64,"realPrice":694.59,"kbPrice":747.19,"call_KB":105.81,"real_KB":92.96,"callCount":"154","realCount":"25"}]